{"openapi":"3.1.0","info":{"title":"Secoraa Backend","version":"0.1.0"},"paths":{"/auth/login":{"post":{"tags":["Auth"],"summary":"Login","operationId":"login_auth_login_post","requestBody":{"content":{"application/json":{"schema":{"$ref":"#/components/schemas/LoginRequest"}}},"required":true},"responses":{"200":{"description":"Successful Response","content":{"application/json":{"schema":{"$ref":"#/components/schemas/TokenResponse"}}}},"422":{"description":"Validation Error","content":{"application/json":{"schema":{"$ref":"#/components/schemas/HTTPValidationError"}}}}}}},"/auth/signup":{"post":{"tags":["Auth"],"summary":"Signup","description":"Onboard a user (create username + password).","operationId":"signup_auth_signup_post","requestBody":{"content":{"application/json":{"schema":{"$ref":"#/components/schemas/SignupRequest"}}},"required":true},"responses":{"200":{"description":"Successful Response","content":{"application/json":{"schema":{}}}},"422":{"description":"Validation Error","content":{"application/json":{"schema":{"$ref":"#/components/schemas/HTTPValidationError"}}}}}}},"/auth/token":{"get":{"tags":["Auth"],"summary":"Get Token","operationId":"get_token_auth_token_get","responses":{"200":{"description":"Successful Response","content":{"application/json":{"schema":{"$ref":"#/components/schemas/TokenClaimsResponse"}}}}},"security":[{"HTTPBearer":[]}]}},"/vulnerabilities/api-findings":{"get":{"tags":["Vulnerabilities"],"summary":"List Api Findings","operationId":"list_api_findings_vulnerabilities_api_findings_get","security":[{"HTTPBearer":[]}],"parameters":[{"name":"severity","in":"query","required":false,"schema":{"anyOf":[{"type":"string"},{"type":"null"}],"title":"Severity"}},{"name":"scan_id","in":"query","required":false,"schema":{"anyOf":[{"type":"string"},{"type":"null"}],"title":"Scan Id"}}],"responses":{"200":{"description":"Successful Response","content":{"application/json":{"schema":{"type":"object"}}}},"422":{"description":"Validation Error","content":{"application/json":{"schema":{"$ref":"#/components/schemas/HTTPValidationError"}}}}}}},"/vulnerabilities/findings":{"get":{"tags":["Vulnerabilities"],"summary":"List All Findings","operationId":"list_all_findings_vulnerabilities_findings_get","security":[{"HTTPBearer":[]}],"parameters":[{"name":"severity","in":"query","required":false,"schema":{"anyOf":[{"type":"string"},{"type":"null"}],"title":"Severity"}}],"responses":{"200":{"description":"Successful Response","content":{"application/json":{"schema":{"type":"object"}}}},"422":{"description":"Validation Error","content":{"application/json":{"schema":{"$ref":"#/components/schemas/HTTPValidationError"}}}}}}},"/scans/scan":{"get":{"tags":["Run-Scans"],"summary":"Get All Scans","operationId":"get_all_scans_scans_scan_get","responses":{"200":{"description":"Successful Response","content":{"application/json":{"schema":{}}}}},"security":[{"HTTPBearer":[]}]}},"/scans/":{"post":{"tags":["Run-Scans"],"summary":"Create Scan","operationId":"create_scan_scans__post","requestBody":{"content":{"application/json":{"schema":{"$ref":"#/components/schemas/CreateScanRequest"}}},"required":true},"responses":{"200":{"description":"Successful Response","content":{"application/json":{"schema":{}}}},"422":{"description":"Validation Error","content":{"application/json":{"schema":{"$ref":"#/components/schemas/HTTPValidationError"}}}}},"security":[{"HTTPBearer":[]}]}},"/assets/domain":{"get":{"tags":["Assets"],"summary":"Get Domain","operationId":"get_domain_assets_domain_get","responses":{"200":{"description":"Successful Response","content":{"application/json":{"schema":{}}}}},"security":[{"HTTPBearer":[]}]},"post":{"tags":["Assets"],"summary":"Create Domain","operationId":"create_domain_assets_domain_post","requestBody":{"content":{"application/json":{"schema":{"$ref":"#/components/schemas/DomainRequestBody"}}},"required":true},"responses":{"200":{"description":"Successful Response","content":{"application/json":{"schema":{}}}},"422":{"description":"Validation Error","content":{"application/json":{"schema":{"$ref":"#/components/schemas/HTTPValidationError"}}}}},"security":[{"HTTPBearer":[]}]}},"/health":{"get":{"summary":"Health","operationId":"health_health_get","responses":{"200":{"description":"Successful Response","content":{"application/json":{"schema":{}}}}}}}},"components":{"schemas":{"LoginRequest":{"properties":{"username":{"type":"string","minLength":1,"title":"Username"},"password":{"type":"string","minLength":1,"title":"Password"}},"type":"object","required":["username","password"],"title":"LoginRequest"},"SignupRequest":{"properties":{"username":{"type":"string","minLength":3,"title":"Username"},"password":{"type":"string","minLength":8,"title":"Password"},"tenant":{"anyOf":[{"type":"string"},{"type":"null"}],"title":"Tenant"}},"type":"object","required":["username","password"],"title":"SignupRequest"},"TokenResponse":{"properties":{"access_token":{"type":"string","title":"Access Token"},"token_type":{"type":"string","title":"Token Type","default":"bearer"},"expires_in":{"type":"integer","title":"Expires In"}},"type":"object","required":["access_token","expires_in"],"title":"TokenResponse"},"TokenClaimsResponse":{"properties":{"sub":{"type":"string","title":"Sub"},"tenant":{"type":"string","title":"Tenant"},"auth":{"type":"object","title":"Auth"},"iat":{"type":"integer","title":"Iat"},"exp":{"type":"integer","title":"Exp"}},"type":"object","required":["sub","tenant","auth","iat","exp"],"title":"TokenClaimsResponse"},"CreateScanRequest":{"properties":{"scan_name":{"type":"string","title":"Scan Name"},"scan_type":{"type":"string","title":"Scan Type"},"payload":{"$ref":"#/components/schemas/GenericScanPayload"}},"type":"object","required":["scan_name","scan_type","payload"],"title":"CreateScanRequest"},"GenericScanPayload":{"properties":{"domain":{"anyOf":[{"type":"string"},{"type":"null"}],"title":"Domain"}},"type":"object","title":"GenericScanPayload"},"DomainRequestBody":{"properties":{"domain_name":{"type":"string","minLength":3,"title":"Domain Name"}},"type":"object","required":["domain_name"],"title":"DomainRequestBody"},"HTTPValidationError":{"properties":{"detail":{"items":{"$ref":"#/components/schemas/ValidationError"},"type":"array","title":"Detail"}},"type":"object","title":"HTTPValidationError"},"ValidationError":{"properties":{"loc":{"items":{"anyOf":[{"type":"string"},{"type":"integer"}]},"type":"array","title":"Location"},"msg":{"type":"string","title":"Message"},"type":{"type":"string","title":"Error Type"}},"type":"object","required":["loc","msg","type"],"title":"ValidationError"}},"securitySchemes":{"HTTPBearer":{"type":"http","scheme":"bearer"}}}}